hate_detector/__init__.py
hate_detector/detector.py
khater-0.1.1.dist-info/METADATA
khater-0.1.1.dist-info/WHEEL
khater-0.1.1.dist-info/top_level.txt
khater-0.1.1.dist-info/RECORD
