Metadata-Version: 2.4
Name: khater
Version: 0.1.1
Summary: RAG based hate speech detector
Author: YourName
Requires-Python: >=3.9
Requires-Dist: langchain-openai
Requires-Dist: langchain-community
Requires-Dist: faiss-cpu
Requires-Dist: python-dotenv
Dynamic: author
Dynamic: description
Dynamic: description-content-type
Dynamic: requires-dist
Dynamic: requires-python
Dynamic: summary
